asilbek/__init__.py
asilbek/core.py
asilbek-0.1.1.dist-info/licenses/LICENSE 
asilbek-0.1.1.dist-info/METADATA
asilbek-0.1.1.dist-info/WHEEL
asilbek-0.1.1.dist-info/top_level.txt
asilbek-0.1.1.dist-info/RECORD
