Metadata-Version: 2.4
Name: asilbek
Version: 0.1.1
Summary: Sadullayev Asilbek tomonidan yaratilgan Python kutubxona
Author: Asilbek Sadullayev
Requires-Python: >=3.7
License-File: LICENSE 
Dynamic: author
Dynamic: license-file
Dynamic: requires-python
Dynamic: summary
